{
    "ID": 54200,
    "name": "McDermott, Inc. v. AmClyde & River Don Castings",
    "href": "https://api.oyez.org/cases/1993/92-1479",
    "view_count": 0,
    "docket_number": "92-1479",
    "timeline": [
        {
            "event": "Argued",
            "dates": [
                758268000
            ],
            "href": "https://api.oyez.org/case_timeline/case_timeline/37240"
        },
        {
            "event": "Decided",
            "dates": [
                766818000
            ],
            "href": "https://api.oyez.org/case_timeline/case_timeline/37241"
        }
    ],
    "question": null,
    "citation": {
        "volume": "511",
        "page": "202",
        "year": "1994",
        "href": "https://api.oyez.org/case_citation/case_citation/18129"
    },
    "term": "1993",
    "description": null,
    "justia_url": "https://supreme.justia.com/cases/federal/us/511/202/",
    "facts_of_the_case": null,
    "conclusion": null
}