{
    "ID": 54260,
    "name": "In re Sassower",
    "href": "https://api.oyez.org/cases/1993/92-8933",
    "view_count": 0,
    "docket_number": "92-8933",
    "timeline": [
        {
            "event": "Decided",
            "dates": [
                750402000
            ],
            "href": "https://api.oyez.org/case_timeline/case_timeline/37354"
        }
    ],
    "question": null,
    "citation": {
        "volume": "510",
        "page": "4",
        "year": "1993",
        "href": "https://api.oyez.org/case_citation/case_citation/18189"
    },
    "term": "1993",
    "description": null,
    "justia_url": null,
    "facts_of_the_case": null,
    "conclusion": null
}